CHANGES.rst
MANIFEST.in
README.rst
release-howto.rst
setup.cfg
setup.py
okapi/__init__.py
okapi/api.py
okapi.egg-info/PKG-INFO
okapi.egg-info/SOURCES.txt
okapi.egg-info/dependency_links.txt
okapi.egg-info/entry_points.txt
okapi.egg-info/not-zip-safe
okapi.egg-info/requires.txt
okapi.egg-info/top_level.txt