Metadata-Version: 1.1
Name: okapi
Version: 0.12.0
Summary: Okapi
